setup.cfg
setup.py
cdpchaosresource/__init__.py
cdpchaosresource/cpu/__init__.py
cdpchaosresource/cpu/actions.py
cdpchaosresource/cpu/probes.py
cdpchaosresource/memory/__init__.py
cdpchaosresource/memory/actions.py
cdpchaosresource/memory/probes.py
cdpchaosresource/utils/CPUActuator.py
cdpchaosresource/utils/ControllerThread.py
cdpchaosresource/utils/MonitorThread.py
cdpchaosresource/utils/RepeatedTimer.py
cdpchaosresource/utils/__init__.py
vztcdpchaos_resource.egg-info/PKG-INFO
vztcdpchaos_resource.egg-info/SOURCES.txt
vztcdpchaos_resource.egg-info/dependency_links.txt
vztcdpchaos_resource.egg-info/requires.txt
vztcdpchaos_resource.egg-info/top_level.txt