Metadata-Version: 1.2
Name: vztcdpchaos-resource
Version: 1.1.1
Summary: Extension for attacking host resources: CPU, Memory, Disk
Home-page: UNKNOWN
Author: vzt-cdp
License: Apache License Version 2.0
Platform: UNKNOWN
Classifier: License :: Freely Distributable
Classifier: Operating System :: OS Independent
Classifier: License :: OSI Approved :: Apache Software License
Classifier: Programming Language :: Python
Classifier: Programming Language :: Python :: 3
Classifier: Programming Language :: Python :: 3.5
Classifier: Programming Language :: Python :: 3.6
Classifier: Programming Language :: Python :: Implementation
Classifier: Programming Language :: Python :: Implementation :: CPython
Requires-Python: >=3.5.*
